[
  {"foreign":"le voyage","turkish":"seyahat"},
  {"foreign":"voyager","turkish":"seyahat etmek"},
  {"foreign":"réserver","turkish":"rezervasyon yapmak"},
  {"foreign":"l'hôtel","turkish":"otel"},
  {"foreign":"l'aéroport","turkish":"havaalanı"},
  {"foreign":"le billet","turkish":"bilet"},
  {"foreign":"arriver","turkish":"varmak"},
  {"foreign":"partir","turkish":"ayrılmak"},
  {"foreign":"le plan","turkish":"plan"},
  {"foreign":"décider","turkish":"karar vermek"},
  {"foreign":"expliquer","turkish":"açıklamak"},
  {"foreign":"comprendre","turkish":"anlamak"},
  {"foreign":"oublier","turkish":"unutmak"},
  {"foreign":"apprendre","turkish":"öğrenmek"},
  {"foreign":"enseigner","turkish":"öğretmek"},
  {"foreign":"la langue","turkish":"dil"},
  {"foreign":"le mot","turkish":"kelime"},
  {"foreign":"la phrase","turkish":"cümle"},
  {"foreign":"demander","turkish":"sormak"},
  {"foreign":"répondre","turkish":"cevap vermek"},
  {"foreign":"gagner","turkish":"kazanmak"},
  {"foreign":"payer","turkish":"ödemek"},
  {"foreign":"coûter","turkish":"mal olmak"},
  {"foreign":"cher","turkish":"pahalı"},
  {"foreign":"bon marché","turkish":"ucuz"},
  {"foreign":"acheter","turkish":"satın almak"},
  {"foreign":"vendre","turkish":"satmak"},
  {"foreign":"le client","turkish":"müşteri"},
  {"foreign":"ouvrir","turkish":"açmak"},
  {"foreign":"fermer","turkish":"kapatmak"},
  {"foreign":"toujours","turkish":"her zaman"},
  {"foreign":"souvent","turkish":"sık sık"},
  {"foreign":"parfois","turkish":"bazen"},
  {"foreign":"jamais","turkish":"asla"},
  {"foreign":"intéressant","turkish":"ilginç"},
  {"foreign":"ennuyeux","turkish":"sıkıcı"},
  {"foreign":"beau","turkish":"güzel"},
  {"foreign":"laid","turkish":"çirkin"},
  {"foreign":"fort","turkish":"güçlü"},
  {"foreign":"faible","turkish":"zayıf"},
  {"foreign":"malade","turkish":"hasta"},
  {"foreign":"le médecin","turkish":"doktor"},
  {"foreign":"important","turkish":"önemli"},
  {"foreign":"possible","turkish":"mümkün"},
  {"foreign":"impossible","turkish":"imkansız"},
  {"foreign":"sûr","turkish":"emin|güvenli"},
  {"foreign":"dangereux","turkish":"tehlikeli"}
]
