[
  {"foreign": "성공하다", "turkish": "to succeed|to manage"},
  {"foreign": "따르다", "turkish": "to follow"},
  {"foreign": "이끌다", "turkish": "to lead|to guide"},
  {"foreign": "달성하다", "turkish": "to achieve|to reach"},
  {"foreign": "극복하다", "turkish": "to overcome|to surpass"},
  {"foreign": "직면하다", "turkish": "to face|to confront"},
  {"foreign": "참다", "turkish": "to bear|to tolerate"},
  {"foreign": "고통받다", "turkish": "to suffer"},
  {"foreign": "감사하다", "turkish": "to appreciate|to thank"},
  {"foreign": "존중하다", "turkish": "to respect"},
  {"foreign": "용서하다", "turkish": "to forgive"},
  {"foreign": "사과하다", "turkish": "to apologize"},
  {"foreign": "약속하다", "turkish": "to promise"},
  {"foreign": "맹세하다", "turkish": "to swear"},
  {"foreign": "부인하다", "turkish": "to deny"},
  {"foreign": "인정하다", "turkish": "to admit|to recognize"},
  {"foreign": "고백하다", "turkish": "to confess"},
  {"foreign": "밝히다", "turkish": "to reveal"},
  {"foreign": "발견하다", "turkish": "to discover"},
  {"foreign": "발명하다", "turkish": "to invent"},
  {"foreign": "계획하다", "turkish": "to plan|to design"},
  {"foreign": "조직하다", "turkish": "to organize"},
  {"foreign": "준비하다", "turkish": "to prepare"},
  {"foreign": "시도하다", "turkish": "to try"},
  {"foreign": "증명하다", "turkish": "to prove"},
  {"foreign": "기억하다", "turkish": "to remember"},
  {"foreign": "잊다", "turkish": "to forget"},
  {"foreign": "상상하다", "turkish": "to imagine"},
  {"foreign": "가정하다", "turkish": "to suppose|to assume"},
  {"foreign": "추정하다", "turkish": "to presume"},
  {"foreign": "추론하다", "turkish": "to deduce"},
  {"foreign": "결론짓다", "turkish": "to conclude"},
  {"foreign": "분석하다", "turkish": "to analyze"},
  {"foreign": "평가하다", "turkish": "to evaluate|to assess"},
  {"foreign": "판단하다", "turkish": "to judge"},
  {"foreign": "비판하다", "turkish": "to criticize"},
  {"foreign": "칭찬하다", "turkish": "to praise"},
  {"foreign": "조언하다", "turkish": "to advise"},
  {"foreign": "제안하다", "turkish": "to suggest"},
  {"foreign": "제공하다", "turkish": "to offer"},
  {"foreign": "받아들이다", "turkish": "to accept"},
  {"foreign": "거절하다", "turkish": "to refuse"},
  {"foreign": "허락하다", "turkish": "to allow|to permit"},
  {"foreign": "협상하다", "turkish": "to negotiate"},
  {"foreign": "투자하다", "turkish": "to invest"},
  {"foreign": "아끼다", "turkish": "to save|to economize"},
  {"foreign": "쓰다", "turkish": "to spend"},
  {"foreign": "벌다", "turkish": "to earn|to gain"},
  {"foreign": "잃다", "turkish": "to lose"},
  {"foreign": "실패하다", "turkish": "to fail"},
  {"foreign": "성공", "turkish": "success"},
  {"foreign": "실패", "turkish": "failure"},
  {"foreign": "희망", "turkish": "hope"},
  {"foreign": "두려움", "turkish": "fear"},
  {"foreign": "용기", "turkish": "courage"},
  {"foreign": "인내", "turkish": "patience"},
  {"foreign": "지루함", "turkish": "boredom"},
  {"foreign": "열정", "turkish": "enthusiasm"},
  {"foreign": "실망", "turkish": "disappointment"},
  {"foreign": "수치심", "turkish": "shame"},
  {"foreign": "자부심", "turkish": "pride"},
  {"foreign": "겸손", "turkish": "humility"},
  {"foreign": "지혜", "turkish": "wisdom"},
  {"foreign": "어리석음", "turkish": "stupidity"},
  {"foreign": "정직", "turkish": "honesty"},
  {"foreign": "불정직", "turkish": "dishonesty"},
  {"foreign": "충성", "turkish": "loyalty"},
  {"foreign": "배신", "turkish": "betrayal"},
  {"foreign": "우정", "turkish": "friendship"},
  {"foreign": "증오", "turkish": "hatred"},
  {"foreign": "질투", "turkish": "envy|jealousy"},
  {"foreign": "연민", "turkish": "compassion"},
  {"foreign": "무관심", "turkish": "indifference"},
  {"foreign": "연대", "turkish": "solidarity"},
  {"foreign": "정의", "turkish": "justice"},
  {"foreign": "불의", "turkish": "injustice"},
  {"foreign": "자유", "turkish": "freedom|liberty"},
  {"foreign": "노예제", "turkish": "slavery"},
  {"foreign": "평등", "turkish": "equality"},
  {"foreign": "다양성", "turkish": "diversity"},
  {"foreign": "평화", "turkish": "peace"},
  {"foreign": "전쟁", "turkish": "war"},
  {"foreign": "폭력", "turkish": "violence"},
  {"foreign": "비폭력", "turkish": "nonviolence"},
  {"foreign": "해결", "turkish": "resolution|solution"},
  {"foreign": "갈등", "turkish": "conflict"},
  {"foreign": "타협", "turkish": "compromise"},
  {"foreign": "합의", "turkish": "agreement"},
  {"foreign": "불일치", "turkish": "disagreement"},
  {"foreign": "관계", "turkish": "relationship"},
  {"foreign": "책임", "turkish": "responsibility"},
  {"foreign": "의무", "turkish": "duty|obligation"},
  {"foreign": "권리", "turkish": "right"},
  {"foreign": "기회", "turkish": "opportunity"},
  {"foreign": "능력", "turkish": "ability"},
  {"foreign": "가능성", "turkish": "possibility"},
  {"foreign": "현실", "turkish": "reality"},
  {"foreign": "이상", "turkish": "ideal"},
  {"foreign": "진실", "turkish": "truth"},
  {"foreign": "거짓말", "turkish": "lie"}
]
